main.py
DeepDETAILS-0.0.0.dist-info/METADATA
DeepDETAILS-0.0.0.dist-info/WHEEL
DeepDETAILS-0.0.0.dist-info/top_level.txt
DeepDETAILS-0.0.0.dist-info/RECORD
