Metadata-Version: 2.1
Name: DeepDETAILS
Version: 0.0.0
Summary: DeepDETAILS
Author: Li Yao
Requires-Python: >=3.9
